overlap_libs/__init__.py
overlap_libs/over.py
overlap_libs/p.py
overlapslib-0.1.1.dist-info/METADATA
overlapslib-0.1.1.dist-info/WHEEL
overlapslib-0.1.1.dist-info/top_level.txt
overlapslib-0.1.1.dist-info/RECORD
