Metadata-Version: 2.1
Name: overlapslib
Version: 0.1.1
Summary: Detect Overlapped
Home-page: UNKNOWN
Author: luxFoz
Author-email: UNKNOWN
License: MIT
Platform: UNKNOWN
